fastFib/__init__.py
fastFib/mainFile.py
fastFibpkg-0.0.1.dist-info/METADATA
fastFibpkg-0.0.1.dist-info/WHEEL
fastFibpkg-0.0.1.dist-info/top_level.txt
fastFibpkg-0.0.1.dist-info/RECORD
